[
{
    "username": "fionaalhadeff",
    "first": "Fiona",
    "last": "Alhadeff",
    "gradeLevel": 9,
    "clickcount": 0,
    "lasttime": 1610656996755,
    "picked": false
},
{
    "username": "isaacallnutt",
    "first": "Isaac",
    "last": "Allnutt",
    "gradeLevel": 9,
    "clickcount": 0,
    "lasttime": 1610656996755,
    "picked": false
},
{
    "username": "edencampbell",
    "first": "Eden",
    "last": "Campbell",
    "gradeLevel": 9,
    "clickcount": 0,
    "lasttime": 1610656996755,
    "picked": false
},
{
    "username": "aldencutler",
    "first": "Alden",
    "last": "Cutler",
    "gradeLevel": 9,
    "clickcount": 0,
    "lasttime": 1610656996755,
    "picked": false
},
{
    "username": "giangaspar",
    "first": "Gian",
    "last": "Gaspar",
    "gradeLevel": 9,
    "clickcount": 0,
    "lasttime": 1610656996755,
    "picked": false
},
{
    "username": "itaimalakoff",
    "first": "Itai",
    "last": "Malakoff",
    "gradeLevel": 9,
    "clickcount": 0,
    "lasttime": 1610656996755,
    "picked": false
},
{
    "username": "mckenzieroberts",
    "first": "McKenzie",
    "last": "Roberts",
    "gradeLevel": 9,
    "clickcount": 0,
    "lasttime": 1610656996755,
    "picked": false
},
{
    "username": "samsakaguchi",
    "first": "Sam",
    "last": "Sakaguchi",
    "gradeLevel": 9,
    "clickcount": 0,
    "lasttime": 1610656996755,
    "picked": false
},
{
    "username": "lucasandoval",
    "first": "Luca",
    "last": "Sandoval",
    "gradeLevel": 9,
    "clickcount": 0,
    "lasttime": 1610656996755,
    "picked": false
},
{
    "username": "johnsawyer",
    "first": "John",
    "last": "Sawyer",
    "gradeLevel": 9,
    "clickcount": 0,
    "lasttime": 1610656996755,
    "picked": false
},
{
    "username": "emmasindeldempcy",
    "first": "Emma",
    "last": "Sindel-Dempcy",
    "gradeLevel": 9,
    "clickcount": 0,
    "lasttime": 1610656996755,
    "picked": false
}]